TeleVisuals/TeleVisuals.py
TeleVisuals/__init__.py
TeleVisuals-0.0.2.dist-info/LICENSE
TeleVisuals-0.0.2.dist-info/METADATA
TeleVisuals-0.0.2.dist-info/WHEEL
TeleVisuals-0.0.2.dist-info/top_level.txt
TeleVisuals-0.0.2.dist-info/RECORD
