Metadata-Version: 2.1
Name: TeleVisuals
Version: 0.0.2
Summary: A package to help you visualize exports from telegram chats
Home-page: https://github.com/zachlim98/TeleVisuals
Author: Zachary Lim
Author-email: contact@nosparechange.com
License: UNKNOWN
Platform: UNKNOWN
Classifier: Programming Language :: Python :: 3
Classifier: License :: OSI Approved :: MIT License
Classifier: Operating System :: OS Independent
Requires-Python: >=3.6
Requires-Dist: pandas
Requires-Dist: plotly.express
